Annaparavai/__init__.py
Annaparavai/model.py
Annaparavai/utils.py
Annaparavai-0.1.0.dist-info/METADATA
Annaparavai-0.1.0.dist-info/WHEEL
Annaparavai-0.1.0.dist-info/top_level.txt
Annaparavai-0.1.0.dist-info/RECORD
